{
  "dog_id": 54515,
  "dog_name": "Blue Gemstone",
  "sex": "d",
  "colour": "fw",
  "birth_date": "2022-03-23",
  "trainer": "P J R Steward",
  "owner": "Mr P J R Steward",
  "sire": "Magical Bale",
  "dam": "Micks Little Gem",
  "current_form": "53243",
  "overall": {
    "runs": 142,
    "wins": 25,
    "seconds": 25,
    "thirds": 31,
    "places": 81
  },
  "tracks": {
    "Harlow": {
      "runs": 74,
      "wins": 14,
      "seconds": 15,
      "thirds": 14,
      "places": 43
    },
    "Towcester": {
      "runs": 38,
      "wins": 6,
      "seconds": 5,
      "thirds": 9,
      "places": 20
    },
    "Suffolk Downs": {
      "runs": 30,
      "wins": 5,
      "seconds": 5,
      "thirds": 8,
      "places": 18
    }
  },
  "distances": {
    "415": {
      "runs": 72,
      "wins": 13,
      "seconds": 15,
      "thirds": 14,
      "places": 42
    },
    "238": {
      "runs": 2,
      "wins": 1,
      "seconds": 0,
      "thirds": 0,
      "places": 1
    },
    "500": {
      "runs": 38,
      "wins": 6,
      "seconds": 5,
      "thirds": 9,
      "places": 20
    },
    "548": {
      "runs": 11,
      "wins": 2,
      "seconds": 0,
      "thirds": 4,
      "places": 6
    },
    "388": {
      "runs": 19,
      "wins": 3,
      "seconds": 5,
      "thirds": 4,
      "places": 12
    }
  },
  "traps": {
    "1": {
      "runs": 92,
      "wins": 19,
      "seconds": 13,
      "thirds": 21,
      "places": 53
    },
    "2": {
      "runs": 38,
      "wins": 4,
      "seconds": 10,
      "thirds": 9,
      "places": 23
    },
    "3": {
      "runs": 9,
      "wins": 2,
      "seconds": 2,
      "thirds": 1,
      "places": 5
    },
    "4": {
      "runs": 3,
      "wins": 0,
      "seconds": 0,
      "thirds": 0,
      "places": 0
    }
  },
  "classes": {
    "A6": {
      "runs": 44,
      "wins": 9,
      "seconds": 11,
      "thirds": 9,
      "places": 29
    },
    "A5": {
      "runs": 37,
      "wins": 6,
      "seconds": 5,
      "thirds": 7,
      "places": 18
    },
    "A7": {
      "runs": 11,
      "wins": 2,
      "seconds": 3,
      "thirds": 1,
      "places": 6
    },
    "A4": {
      "runs": 16,
      "wins": 4,
      "seconds": 1,
      "thirds": 5,
      "places": 10
    },
    "D4": {
      "runs": 2,
      "wins": 1,
      "seconds": 0,
      "thirds": 0,
      "places": 1
    },
    "A3": {
      "runs": 14,
      "wins": 1,
      "seconds": 3,
      "thirds": 4,
      "places": 8
    },
    "A2": {
      "runs": 2,
      "wins": 0,
      "seconds": 0,
      "thirds": 1,
      "places": 1
    },
    "IV": {
      "runs": 4,
      "wins": 0,
      "seconds": 2,
      "thirds": 0,
      "places": 2
    },
    "S3": {
      "runs": 6,
      "wins": 1,
      "seconds": 0,
      "thirds": 3,
      "places": 4
    },
    "S2": {
      "runs": 4,
      "wins": 1,
      "seconds": 0,
      "thirds": 0,
      "places": 1
    },
    "OR3": {
      "runs": 1,
      "wins": 0,
      "seconds": 0,
      "thirds": 1,
      "places": 1
    },
    "IT": {
      "runs": 1,
      "wins": 0,
      "seconds": 0,
      "thirds": 0,
      "places": 0
    }
  },
  "best_time": 15.44,
  "average_time": 28.24,
  "last_seen": "2026-07-22",
  "win_rate": 17.61,
  "place_rate": 57.04
}