{
  "dog_id": 54542,
  "dog_name": "Alnwick Barney",
  "sex": "d",
  "colour": "bebd",
  "birth_date": "2022-03-31",
  "trainer": "A Harrison",
  "owner": "Miss A Harrison",
  "sire": "King Turbo",
  "dam": "Move Over Evie",
  "current_form": "55133",
  "overall": {
    "runs": 110,
    "wins": 18,
    "seconds": 26,
    "thirds": 23,
    "places": 67
  },
  "tracks": {
    "Newcastle": {
      "runs": 110,
      "wins": 18,
      "seconds": 26,
      "thirds": 23,
      "places": 67
    }
  },
  "distances": {
    "480": {
      "runs": 110,
      "wins": 18,
      "seconds": 26,
      "thirds": 23,
      "places": 67
    }
  },
  "traps": {
    "6": {
      "runs": 103,
      "wins": 16,
      "seconds": 23,
      "thirds": 23,
      "places": 62
    },
    "5": {
      "runs": 7,
      "wins": 2,
      "seconds": 3,
      "thirds": 0,
      "places": 5
    }
  },
  "classes": {
    "A5": {
      "runs": 41,
      "wins": 4,
      "seconds": 4,
      "thirds": 12,
      "places": 20
    },
    "A4": {
      "runs": 16,
      "wins": 3,
      "seconds": 5,
      "thirds": 4,
      "places": 12
    },
    "A3": {
      "runs": 4,
      "wins": 0,
      "seconds": 0,
      "thirds": 1,
      "places": 1
    },
    "A6": {
      "runs": 26,
      "wins": 5,
      "seconds": 8,
      "thirds": 4,
      "places": 17
    },
    "A7": {
      "runs": 12,
      "wins": 4,
      "seconds": 3,
      "thirds": 2,
      "places": 9
    },
    "A8": {
      "runs": 11,
      "wins": 2,
      "seconds": 6,
      "thirds": 0,
      "places": 8
    }
  },
  "best_time": 29.25,
  "average_time": 29.8,
  "last_seen": "2026-06-30",
  "win_rate": 16.36,
  "place_rate": 60.91
}