{
  "dog_id": 60616,
  "dog_name": "Sovereign Poppy",
  "sex": "b",
  "colour": "bd",
  "birth_date": "2023-04-12",
  "trainer": "J A Knape",
  "owner": "Mr J A Knape",
  "sire": "Ballyhimikin Jet",
  "dam": "Commons Jet",
  "current_form": "51353",
  "overall": {
    "runs": 62,
    "wins": 12,
    "seconds": 12,
    "thirds": 9,
    "places": 33
  },
  "tracks": {
    "Towcester": {
      "runs": 22,
      "wins": 6,
      "seconds": 2,
      "thirds": 2,
      "places": 10
    },
    "Dunstall Park": {
      "runs": 13,
      "wins": 1,
      "seconds": 7,
      "thirds": 1,
      "places": 9
    },
    "Perry Barr": {
      "runs": 27,
      "wins": 5,
      "seconds": 3,
      "thirds": 6,
      "places": 14
    }
  },
  "distances": {
    "500": {
      "runs": 22,
      "wins": 6,
      "seconds": 2,
      "thirds": 2,
      "places": 10
    },
    "480": {
      "runs": 33,
      "wins": 5,
      "seconds": 9,
      "thirds": 6,
      "places": 20
    },
    "270": {
      "runs": 1,
      "wins": 0,
      "seconds": 1,
      "thirds": 0,
      "places": 1
    },
    "275": {
      "runs": 6,
      "wins": 1,
      "seconds": 0,
      "thirds": 1,
      "places": 2
    }
  },
  "traps": {
    "1": {
      "runs": 42,
      "wins": 9,
      "seconds": 8,
      "thirds": 7,
      "places": 24
    },
    "2": {
      "runs": 15,
      "wins": 3,
      "seconds": 4,
      "thirds": 1,
      "places": 8
    },
    "4": {
      "runs": 1,
      "wins": 0,
      "seconds": 0,
      "thirds": 0,
      "places": 0
    },
    "3": {
      "runs": 4,
      "wins": 0,
      "seconds": 0,
      "thirds": 1,
      "places": 1
    }
  },
  "classes": {
    "A6": {
      "runs": 21,
      "wins": 4,
      "seconds": 3,
      "thirds": 5,
      "places": 12
    },
    "A5": {
      "runs": 16,
      "wins": 1,
      "seconds": 8,
      "thirds": 1,
      "places": 10
    },
    "A7": {
      "runs": 10,
      "wins": 5,
      "seconds": 0,
      "thirds": 1,
      "places": 6
    },
    "A8": {
      "runs": 1,
      "wins": 1,
      "seconds": 0,
      "thirds": 0,
      "places": 1
    },
    "D3": {
      "runs": 5,
      "wins": 0,
      "seconds": 1,
      "thirds": 1,
      "places": 2
    },
    "D4": {
      "runs": 1,
      "wins": 1,
      "seconds": 0,
      "thirds": 0,
      "places": 1
    },
    "HP": {
      "runs": 3,
      "wins": 0,
      "seconds": 0,
      "thirds": 1,
      "places": 1
    },
    "A4": {
      "runs": 4,
      "wins": 0,
      "seconds": 0,
      "thirds": 0,
      "places": 0
    },
    "D2": {
      "runs": 1,
      "wins": 0,
      "seconds": 0,
      "thirds": 0,
      "places": 0
    }
  },
  "best_time": 16.37,
  "average_time": 28.34,
  "last_seen": "2026-07-04",
  "win_rate": 19.35,
  "place_rate": 53.23
}