{
  "dog_id": 61812,
  "dog_name": "Hollyoak Cleo",
  "sex": "b",
  "colour": "bebd",
  "birth_date": "2022-12-05",
  "trainer": "R W Butler",
  "owner": "Hollyoak Syndicate",
  "sire": "Hollyoak Hector",
  "dam": "Droopys Baton",
  "current_form": "23524",
  "overall": {
    "runs": 29,
    "wins": 3,
    "seconds": 8,
    "thirds": 5,
    "places": 16
  },
  "tracks": {
    "Central Park": {
      "runs": 29,
      "wins": 3,
      "seconds": 8,
      "thirds": 5,
      "places": 16
    }
  },
  "distances": {
    "277": {
      "runs": 29,
      "wins": 3,
      "seconds": 8,
      "thirds": 5,
      "places": 16
    }
  },
  "traps": {
    "1": {
      "runs": 22,
      "wins": 3,
      "seconds": 6,
      "thirds": 3,
      "places": 12
    },
    "2": {
      "runs": 5,
      "wins": 0,
      "seconds": 2,
      "thirds": 1,
      "places": 3
    },
    "3": {
      "runs": 2,
      "wins": 0,
      "seconds": 0,
      "thirds": 1,
      "places": 1
    }
  },
  "classes": {
    "D4": {
      "runs": 15,
      "wins": 2,
      "seconds": 5,
      "thirds": 3,
      "places": 10
    },
    "D3": {
      "runs": 8,
      "wins": 0,
      "seconds": 1,
      "thirds": 1,
      "places": 2
    },
    "D5": {
      "runs": 6,
      "wins": 1,
      "seconds": 2,
      "thirds": 1,
      "places": 4
    }
  },
  "best_time": 16.8,
  "average_time": 17.28,
  "last_seen": "2026-07-13",
  "win_rate": 10.34,
  "place_rate": 55.17
}