{
  "dog_id": 62252,
  "dog_name": "Wanfourtoeknee",
  "sex": "d",
  "colour": "be",
  "birth_date": "2023-10-10",
  "trainer": "C S Fereday",
  "owner": "Miss C K Ramsbottom",
  "sire": "Ballymac Cashout",
  "dam": "Droopys Daffy",
  "current_form": "54126",
  "overall": {
    "runs": 60,
    "wins": 17,
    "seconds": 14,
    "thirds": 8,
    "places": 39
  },
  "tracks": {
    "Monmore": {
      "runs": 50,
      "wins": 13,
      "seconds": 11,
      "thirds": 8,
      "places": 32
    },
    "Nottingham": {
      "runs": 10,
      "wins": 4,
      "seconds": 3,
      "thirds": 0,
      "places": 7
    }
  },
  "distances": {
    "264": {
      "runs": 49,
      "wins": 13,
      "seconds": 11,
      "thirds": 8,
      "places": 32
    },
    "480": {
      "runs": 1,
      "wins": 0,
      "seconds": 0,
      "thirds": 0,
      "places": 0
    },
    "305": {
      "runs": 5,
      "wins": 2,
      "seconds": 2,
      "thirds": 0,
      "places": 4
    },
    "500": {
      "runs": 5,
      "wins": 2,
      "seconds": 1,
      "thirds": 0,
      "places": 3
    }
  },
  "traps": {
    "6": {
      "runs": 48,
      "wins": 12,
      "seconds": 12,
      "thirds": 7,
      "places": 31
    },
    "5": {
      "runs": 12,
      "wins": 5,
      "seconds": 2,
      "thirds": 1,
      "places": 8
    }
  },
  "classes": {
    "D1": {
      "runs": 22,
      "wins": 4,
      "seconds": 4,
      "thirds": 3,
      "places": 11
    },
    "D2": {
      "runs": 18,
      "wins": 6,
      "seconds": 6,
      "thirds": 1,
      "places": 13
    },
    "OR3": {
      "runs": 7,
      "wins": 1,
      "seconds": 1,
      "thirds": 4,
      "places": 6
    },
    "OR": {
      "runs": 4,
      "wins": 1,
      "seconds": 2,
      "thirds": 0,
      "places": 3
    },
    "D3": {
      "runs": 3,
      "wins": 3,
      "seconds": 0,
      "thirds": 0,
      "places": 3
    },
    "A7": {
      "runs": 2,
      "wins": 1,
      "seconds": 0,
      "thirds": 0,
      "places": 1
    },
    "A6": {
      "runs": 3,
      "wins": 0,
      "seconds": 1,
      "thirds": 0,
      "places": 1
    },
    "A8": {
      "runs": 1,
      "wins": 1,
      "seconds": 0,
      "thirds": 0,
      "places": 1
    }
  },
  "best_time": 15.31,
  "average_time": 17.45,
  "last_seen": "2026-07-14",
  "win_rate": 28.33,
  "place_rate": 65.0
}