{
  "dog_id": 67267,
  "dog_name": "Hollyhill Bullet",
  "sex": "d",
  "colour": "bkw",
  "birth_date": "2024-08-13",
  "trainer": "F Macklin",
  "owner": "Mr F Macklin",
  "sire": "Droopys Got It",
  "dam": "Bo Shine Bullet",
  "current_form": "12112",
  "overall": {
    "runs": 13,
    "wins": 6,
    "seconds": 5,
    "thirds": 1,
    "places": 12
  },
  "tracks": {
    "Nottingham": {
      "runs": 12,
      "wins": 5,
      "seconds": 5,
      "thirds": 1,
      "places": 11
    },
    "Central Park": {
      "runs": 1,
      "wins": 1,
      "seconds": 0,
      "thirds": 0,
      "places": 1
    }
  },
  "distances": {
    "500": {
      "runs": 12,
      "wins": 5,
      "seconds": 5,
      "thirds": 1,
      "places": 11
    },
    "491": {
      "runs": 1,
      "wins": 1,
      "seconds": 0,
      "thirds": 0,
      "places": 1
    }
  },
  "traps": {
    "5": {
      "runs": 3,
      "wins": 2,
      "seconds": 1,
      "thirds": 0,
      "places": 3
    },
    "4": {
      "runs": 5,
      "wins": 2,
      "seconds": 2,
      "thirds": 1,
      "places": 5
    },
    "3": {
      "runs": 5,
      "wins": 2,
      "seconds": 2,
      "thirds": 0,
      "places": 4
    }
  },
  "classes": {
    "A1": {
      "runs": 1,
      "wins": 0,
      "seconds": 1,
      "thirds": 0,
      "places": 1
    },
    "A2": {
      "runs": 1,
      "wins": 1,
      "seconds": 0,
      "thirds": 0,
      "places": 1
    },
    "A3": {
      "runs": 2,
      "wins": 1,
      "seconds": 1,
      "thirds": 0,
      "places": 2
    },
    "OR": {
      "runs": 1,
      "wins": 1,
      "seconds": 0,
      "thirds": 0,
      "places": 1
    },
    "A4": {
      "runs": 3,
      "wins": 1,
      "seconds": 1,
      "thirds": 1,
      "places": 3
    },
    "A5": {
      "runs": 3,
      "wins": 1,
      "seconds": 1,
      "thirds": 0,
      "places": 2
    },
    "A6": {
      "runs": 2,
      "wins": 1,
      "seconds": 1,
      "thirds": 0,
      "places": 2
    }
  },
  "best_time": 29.29,
  "average_time": 30.22,
  "last_seen": "2026-06-19",
  "win_rate": 46.15,
  "place_rate": 92.31
}