{
  "dog_id": 67831,
  "dog_name": "Kilgarran Des",
  "sex": "d",
  "colour": "bd",
  "birth_date": "2024-08-09",
  "trainer": "J D T Allen",
  "owner": "Mr J D T Allen",
  "sire": "Pestana",
  "dam": "Kilgarran Maid",
  "current_form": "51655",
  "overall": {
    "runs": 15,
    "wins": 2,
    "seconds": 4,
    "thirds": 2,
    "places": 8
  },
  "tracks": {
    "Harlow": {
      "runs": 15,
      "wins": 2,
      "seconds": 4,
      "thirds": 2,
      "places": 8
    }
  },
  "distances": {
    "238": {
      "runs": 15,
      "wins": 2,
      "seconds": 4,
      "thirds": 2,
      "places": 8
    }
  },
  "traps": {
    "3": {
      "runs": 12,
      "wins": 2,
      "seconds": 3,
      "thirds": 1,
      "places": 6
    },
    "2": {
      "runs": 2,
      "wins": 0,
      "seconds": 0,
      "thirds": 1,
      "places": 1
    },
    "4": {
      "runs": 1,
      "wins": 0,
      "seconds": 1,
      "thirds": 0,
      "places": 1
    }
  },
  "classes": {
    "D5": {
      "runs": 15,
      "wins": 2,
      "seconds": 4,
      "thirds": 2,
      "places": 8
    }
  },
  "best_time": 15.66,
  "average_time": 16.04,
  "last_seen": "2026-07-10",
  "win_rate": 13.33,
  "place_rate": 53.33
}