{
  "dog_id": 68259,
  "dog_name": "Tickets Bang",
  "sex": "b",
  "colour": "bk",
  "birth_date": "2024-08-01",
  "trainer": "P A Curtin",
  "owner": "Mr A Johnston",
  "sire": "My Redeemer",
  "dam": "Rossetti Uk",
  "current_form": "123",
  "overall": {
    "runs": 3,
    "wins": 1,
    "seconds": 1,
    "thirds": 1,
    "places": 3
  },
  "tracks": {
    "Monmore": {
      "runs": 3,
      "wins": 1,
      "seconds": 1,
      "thirds": 1,
      "places": 3
    }
  },
  "distances": {
    "480": {
      "runs": 3,
      "wins": 1,
      "seconds": 1,
      "thirds": 1,
      "places": 3
    }
  },
  "traps": {
    "3": {
      "runs": 2,
      "wins": 0,
      "seconds": 1,
      "thirds": 1,
      "places": 2
    },
    "2": {
      "runs": 1,
      "wins": 1,
      "seconds": 0,
      "thirds": 0,
      "places": 1
    }
  },
  "classes": {
    "A10": {
      "runs": 2,
      "wins": 1,
      "seconds": 0,
      "thirds": 1,
      "places": 2
    },
    "A9": {
      "runs": 1,
      "wins": 0,
      "seconds": 1,
      "thirds": 0,
      "places": 1
    }
  },
  "best_time": 29.92,
  "average_time": 30.17,
  "last_seen": "2026-06-15",
  "win_rate": 33.33,
  "place_rate": 100.0
}