{
  "dog_id": 68296,
  "dog_name": "Ashtons Oakley",
  "sex": "d",
  "colour": "bd",
  "birth_date": "2024-07-10",
  "trainer": "S W Deakin",
  "owner": "Mr D S Ashton",
  "sire": "Dromana Bucko",
  "dam": "Mary Goodnight",
  "current_form": "653",
  "overall": {
    "runs": 4,
    "wins": 0,
    "seconds": 0,
    "thirds": 1,
    "places": 1
  },
  "tracks": {
    "Dunstall Park": {
      "runs": 4,
      "wins": 0,
      "seconds": 0,
      "thirds": 1,
      "places": 1
    }
  },
  "distances": {
    "480": {
      "runs": 4,
      "wins": 0,
      "seconds": 0,
      "thirds": 1,
      "places": 1
    }
  },
  "traps": {
    "6": {
      "runs": 3,
      "wins": 0,
      "seconds": 0,
      "thirds": 1,
      "places": 1
    },
    "5": {
      "runs": 1,
      "wins": 0,
      "seconds": 0,
      "thirds": 0,
      "places": 0
    }
  },
  "classes": {
    "A8": {
      "runs": 3,
      "wins": 0,
      "seconds": 0,
      "thirds": 1,
      "places": 1
    },
    "A7": {
      "runs": 1,
      "wins": 0,
      "seconds": 0,
      "thirds": 0,
      "places": 0
    }
  },
  "best_time": 29.77,
  "average_time": 30.3,
  "last_seen": "2026-06-29",
  "win_rate": 0.0,
  "place_rate": 25.0
}