{
  "date": "2026-07-03",
  "course": "Beverley",
  "time": "19:10",
  "race_name": "Jacksons Of Yorkshire Handicap",
  "winner": "Hatamoto",
  "winner_sp": "5/6",
  "winner_rank": 1,
  "winner_score": 67,
  "top_pick": "Hatamoto",
  "top_pick_score": 67,
  "top_pick_win": true,
  "top_3_hit": true,
  "review": "EXCELLENT",
  "learning_notes": [
    "Pulse top pick won.",
    "Top pick was Hatamoto with score 67."
  ],
  "top_3": [
    {
      "rank": 1,
      "horse": "Hatamoto",
      "pulse_score": 67
    },
    {
      "rank": 2,
      "horse": "Regal Knight",
      "pulse_score": 62
    },
    {
      "rank": 3,
      "horse": "Mali Star",
      "pulse_score": 57
    }
  ]
}