{
  "horse": "Hayday",
  "horse_id": "hrs_37603839",
  "age": 6,
  "sex": "gelding",
  "latest_course": "Sha Tin",
  "latest_time": "10:00",
  "latest_race": "Lam Tsuen River Handicap (Class 4) (Course B) (Turf)",
  "latest_date": "2026-06-27",
  "latest_distance_f": 6.0,
  "latest_class": "",
  "latest_going": "Good",
  "latest_surface": "Turf",
  "latest_trainer": "P F Yiu",
  "latest_jockey": "Nichola Yuen(10)",
  "latest_draw": 12,
  "latest_weight_lbs": 129,
  "official_rating": "54",
  "recent_form": "-35659",
  "last_run_days": 31,
  "profile_runs": 2,
  "courses_seen": {
    "Sha Tin": 2
  },
  "distances_seen": {
    "6.0": 2
  },
  "goings_seen": {
    "Good": 2
  },
  "classes_seen": {},
  "trainers_seen": {
    "P F Yiu": 2
  },
  "jockeys_seen": {
    "Nichola Yuen(10)": 2
  },
  "average_pulse_score": 0,
  "best_pulse_score": null,
  "latest_pulse_score": null,
  "latest_notes": [],
  "runs": [
    {
      "source": "the_racing_api",
      "race_id": "rac_12007190",
      "course": "Sha Tin",
      "date": "2026-06-27",
      "off_time": "10:00",
      "off_dt": "2026-06-27T10:00:00+01:00",
      "race_name": "Lam Tsuen River Handicap (Class 4) (Course B) (Turf)",
      "distance_f": 6.0,
      "race_class": "",
      "race_type": "Flat",
      "going": "Good",
      "surface": "Turf",
      "field_size": 14,
      "horse": "Hayday",
      "horse_id": "hrs_37603839",
      "age": 6,
      "sex": "gelding",
      "trainer": "P F Yiu",
      "trainer_id": "trn_125424",
      "jockey": "Nichola Yuen(10)",
      "jockey_id": "jky_308487",
      "draw": 12,
      "number": 5,
      "lbs": 129,
      "ofr": "54",
      "last_run": 31,
      "form": "-35659",
      "headgear": "",
      "_stored_at": "2026-06-27T10:06:22.974908+00:00"
    },
    {
      "source": "the_racing_api",
      "race_id": "rac_12007190",
      "course": "Sha Tin",
      "date": "2026-06-27",
      "off_time": "10:00",
      "off_dt": "2026-06-27T10:00:00+01:00",
      "race_name": "Lam Tsuen River Handicap (Class 4) (Course B) (Turf)",
      "distance_f": 6.0,
      "race_class": "",
      "race_type": "Flat",
      "going": "Good",
      "surface": "Turf",
      "field_size": 14,
      "horse": "Hayday",
      "horse_id": "hrs_37603839",
      "age": 6,
      "sex": "gelding",
      "trainer": "P F Yiu",
      "trainer_id": "trn_125424",
      "jockey": "Nichola Yuen(10)",
      "jockey_id": "jky_308487",
      "draw": 12,
      "number": 5,
      "lbs": 129,
      "ofr": "54",
      "last_run": 31,
      "form": "-35659",
      "headgear": "",
      "_stored_at": "2026-06-28T12:42:50.422611+00:00"
    }
  ],
  "profile_notes": []
}