{"horse":"Penzance","horse_id":"hrs_34961493","age":6,"sex":"gelding","latest_course":"Stratford","latest_time":"6:48","latest_race":"Racehorse Ownership From 25 Pound At racingclub.com Maiden Hurdle (GBB Race)","latest_date":"2026-06-30","latest_distance_f":18.5,"latest_class":"Class 4","latest_going":"Good To Firm","latest_surface":"Turf","latest_trainer":"John Joseph Hanlon","latest_jockey":"Paddy Hanlon(5)","latest_draw":0,"latest_weight_lbs":158,"official_rating":"-","recent_form":"3-4","last_run_days":14,"profile_runs":1,"courses_seen":{"Stratford":1},"distances_seen":{"18.5":1},"goings_seen":{"Good To Firm":1},"classes_seen":{"Class 4":1},"trainers_seen":{"John Joseph Hanlon":1},"jockeys_seen":{"Paddy Hanlon(5)":1},"average_pulse_score":0,"best_pulse_score":null,"latest_pulse_score":67,"latest_notes":["Positive recent form","Good recent run timing","Ideal layoff profile +2","Helpful draw","Race class strength +2","Stable in form +2 (1/2 last 14 days)","Jockey in form +2 (1/2 last 14 days)"],"runs":[{"source":"the_racing_api","race_id":"rac_11987222","course":"Stratford","date":"2026-06-30","off_time":"6:48","off_dt":"2026-06-30T18:48:00+01:00","race_name":"Racehorse Ownership From 25 Pound At racingclub.com Maiden Hurdle (GBB Race)","distance_f":18.5,"race_class":"Class 4","race_type":"Hurdle","going":"Good To Firm","surface":"Turf","field_size":8,"horse":"Penzance","horse_id":"hrs_34961493","age":6,"sex":"gelding","trainer":"John Joseph Hanlon","trainer_id":"trn_169605","jockey":"Paddy Hanlon(5)","jockey_id":"jky_308520","draw":0,"number":5,"lbs":158,"ofr":"-","last_run":14,"form":"3-4","headgear":"","_stored_at":"2026-06-30T01:49:58.029546+00:00"}],"profile_notes":["Recent run timing"],"favourite_course":{"value":"Stratford","runs":1},"favourite_distance":{"value":18.5,"runs":1},"favourite_going":{"value":"Good To Firm","runs":1},"favourite_class":{"value":"Class 4","runs":1},"course_suitability_score":90,"distance_suitability_score":90,"going_suitability_score":90,"class_suitability_score":90,"suitability_score":90,"horse_intelligence_score":57,"profile_strengths":["Today's course matches strongest profile pattern","Today's distance matches strongest profile pattern","Today's going matches known profile preference","Race class matches common profile level","Positive latest Pulse Score"],"profile_cautions":["Limited stored profile data"],"enrich_version":"profile_enrich_v2","enrich_signature":{"latest_course":"Stratford","latest_distance_f":18.5,"latest_going":"Good To Firm","latest_class":"Class 4","latest_pulse_score":67,"average_pulse_score":0,"profile_runs":1,"runs_count":1},"latest_result":{"source":"sporting_life_enriched","result_date":"2026-07-12","course":"Stratford","race_time":"14:35","race_name":"University Hospitals Birmingham Charity Maiden Hurdle (GBB Race)","race_id":"rac_11987885","status":null,"finish_position":2,"sp":"7/4","favourite_position":null,"going":"Good to Firm","distance":"2m 70y","field_size":"7","trainer":"John Joseph Hanlon","jockey":"Paddy Hanlon(5)","distance_beaten":null,"won":false,"placed":true,"attached_at":"2026-07-15T14:31:30"},"latest_result_position":2,"latest_result_sp":"7/4","latest_result_won":false,"latest_result_placed":true,"latest_result_date":"2026-07-12"}